Compiled from "Graph.java"
public class com.turbulence6th.dijkstra.Graph {
  public com.turbulence6th.dijkstra.Graph();
    Code:
       0: aload_0
       1: invokespecial #12                 // Method java/lang/Object."<init>":()V
       4: aload_0
       5: new           #14                 // class java/util/ArrayList
       8: dup
       9: invokespecial #16                 // Method java/util/ArrayList."<init>":()V
      12: putfield      #17                 // Field nodes:Ljava/util/List;
      15: return

  public void addEdge(java.lang.String, java.lang.String, int);
    Code:
       0: aload_0
       1: getfield      #17                 // Field nodes:Ljava/util/List;
       4: invokeinterface #25,  1           // InterfaceMethod java/util/List.stream:()Ljava/util/stream/Stream;
       9: aload_1
      10: invokedynamic #34,  0             // InvokeDynamic #0:test:(Ljava/lang/String;)Ljava/util/function/Predicate;
      15: invokeinterface #35,  2           // InterfaceMethod java/util/stream/Stream.filter:(Ljava/util/function/Predicate;)Ljava/util/stream/Stream;
      20: invokeinterface #41,  1           // InterfaceMethod java/util/stream/Stream.findFirst:()Ljava/util/Optional;
      25: aload_0
      26: aload_1
      27: invokedynamic #48,  0             // InvokeDynamic #1:get:(Lcom/turbulence6th/dijkstra/Graph;Ljava/lang/String;)Ljava/util/function/Supplier;
      32: invokevirtual #49                 // Method java/util/Optional.orElseGet:(Ljava/util/function/Supplier;)Ljava/lang/Object;
      35: checkcast     #55                 // class com/turbulence6th/dijkstra/Graph$Node
      38: astore        4
      40: aload_0
      41: getfield      #17                 // Field nodes:Ljava/util/List;
      44: invokeinterface #25,  1           // InterfaceMethod java/util/List.stream:()Ljava/util/stream/Stream;
      49: aload_2
      50: invokedynamic #57,  0             // InvokeDynamic #2:test:(Ljava/lang/String;)Ljava/util/function/Predicate;
      55: invokeinterface #35,  2           // InterfaceMethod java/util/stream/Stream.filter:(Ljava/util/function/Predicate;)Ljava/util/stream/Stream;
      60: invokeinterface #41,  1           // InterfaceMethod java/util/stream/Stream.findFirst:()Ljava/util/Optional;
      65: aload_0
      66: aload_2
      67: invokedynamic #58,  0             // InvokeDynamic #3:get:(Lcom/turbulence6th/dijkstra/Graph;Ljava/lang/String;)Ljava/util/function/Supplier;
      72: invokevirtual #49                 // Method java/util/Optional.orElseGet:(Ljava/util/function/Supplier;)Ljava/lang/Object;
      75: checkcast     #55                 // class com/turbulence6th/dijkstra/Graph$Node
      78: astore        5
      80: aload         4
      82: getfield      #59                 // Field com/turbulence6th/dijkstra/Graph$Node.edges:Ljava/util/List;
      85: new           #62                 // class com/turbulence6th/dijkstra/Graph$Edge
      88: dup
      89: aload_0
      90: aload         5
      92: iload_3
      93: invokespecial #64                 // Method com/turbulence6th/dijkstra/Graph$Edge."<init>":(Lcom/turbulence6th/dijkstra/Graph;Lcom/turbulence6th/dijkstra/Graph$Node;I)V
      96: invokeinterface #67,  2           // InterfaceMethod java/util/List.add:(Ljava/lang/Object;)Z
     101: pop
     102: aload         5
     104: getfield      #59                 // Field com/turbulence6th/dijkstra/Graph$Node.edges:Ljava/util/List;
     107: new           #62                 // class com/turbulence6th/dijkstra/Graph$Edge
     110: dup
     111: aload_0
     112: aload         4
     114: iload_3
     115: invokespecial #64                 // Method com/turbulence6th/dijkstra/Graph$Edge."<init>":(Lcom/turbulence6th/dijkstra/Graph;Lcom/turbulence6th/dijkstra/Graph$Node;I)V
     118: invokeinterface #67,  2           // InterfaceMethod java/util/List.add:(Ljava/lang/Object;)Z
     123: pop
     124: return

  public void dijkstra(java.lang.String, java.lang.String);
    Code:
       0: aload_0
       1: getfield      #17                 // Field nodes:Ljava/util/List;
       4: invokeinterface #25,  1           // InterfaceMethod java/util/List.stream:()Ljava/util/stream/Stream;
       9: aload_1
      10: invokedynamic #81,  0             // InvokeDynamic #4:test:(Ljava/lang/String;)Ljava/util/function/Predicate;
      15: invokeinterface #35,  2           // InterfaceMethod java/util/stream/Stream.filter:(Ljava/util/function/Predicate;)Ljava/util/stream/Stream;
      20: invokeinterface #41,  1           // InterfaceMethod java/util/stream/Stream.findFirst:()Ljava/util/Optional;
      25: invokevirtual #82                 // Method java/util/Optional.get:()Ljava/lang/Object;
      28: checkcast     #55                 // class com/turbulence6th/dijkstra/Graph$Node
      31: astore_3
      32: aload_3
      33: iconst_0
      34: putfield      #85                 // Field com/turbulence6th/dijkstra/Graph$Node.minDistance:I
      37: new           #88                 // class java/util/LinkedList
      40: dup
      41: invokespecial #90                 // Method java/util/LinkedList."<init>":()V
      44: astore        4
      46: aload         4
      48: aload_3
      49: invokeinterface #91,  2           // InterfaceMethod java/util/Queue.add:(Ljava/lang/Object;)Z
      54: pop
      55: goto          183
      58: aload         4
      60: invokeinterface #94,  1           // InterfaceMethod java/util/Queue.poll:()Ljava/lang/Object;
      65: checkcast     #55                 // class com/turbulence6th/dijkstra/Graph$Node
      68: astore        5
      70: aload         5
      72: getfield      #97                 // Field com/turbulence6th/dijkstra/Graph$Node.isVisited:Z
      75: ifeq          81
      78: goto          183
      81: aload         5
      83: iconst_1
      84: putfield      #97                 // Field com/turbulence6th/dijkstra/Graph$Node.isVisited:Z
      87: aload         5
      89: getfield      #59                 // Field com/turbulence6th/dijkstra/Graph$Node.edges:Ljava/util/List;
      92: invokeinterface #101,  1          // InterfaceMethod java/util/List.iterator:()Ljava/util/Iterator;
      97: astore        7
      99: goto          173
     102: aload         7
     104: invokeinterface #105,  1          // InterfaceMethod java/util/Iterator.next:()Ljava/lang/Object;
     109: checkcast     #62                 // class com/turbulence6th/dijkstra/Graph$Edge
     112: astore        6
     114: aload         6
     116: getfield      #110                // Field com/turbulence6th/dijkstra/Graph$Edge.node:Lcom/turbulence6th/dijkstra/Graph$Node;
     119: astore        8
     121: aload         6
     123: getfield      #113                // Field com/turbulence6th/dijkstra/Graph$Edge.distance:I
     126: aload         5
     128: getfield      #85                 // Field com/turbulence6th/dijkstra/Graph$Node.minDistance:I
     131: iadd
     132: aload         8
     134: getfield      #85                 // Field com/turbulence6th/dijkstra/Graph$Node.minDistance:I
     137: if_icmpge     163
     140: aload         8
     142: aload         6
     144: getfield      #113                // Field com/turbulence6th/dijkstra/Graph$Edge.distance:I
     147: aload         5
     149: getfield      #85                 // Field com/turbulence6th/dijkstra/Graph$Node.minDistance:I
     152: iadd
     153: putfield      #85                 // Field com/turbulence6th/dijkstra/Graph$Node.minDistance:I
     156: aload         8
     158: aload         5
     160: putfield      #115                // Field com/turbulence6th/dijkstra/Graph$Node.minEdge:Lcom/turbulence6th/dijkstra/Graph$Node;
     163: aload         4
     165: aload         8
     167: invokeinterface #91,  2           // InterfaceMethod java/util/Queue.add:(Ljava/lang/Object;)Z
     172: pop
     173: aload         7
     175: invokeinterface #118,  1          // InterfaceMethod java/util/Iterator.hasNext:()Z
     180: ifne          102
     183: aload         4
     185: invokeinterface #122,  1          // InterfaceMethod java/util/Queue.isEmpty:()Z
     190: ifeq          58
     193: aload_0
     194: getfield      #17                 // Field nodes:Ljava/util/List;
     197: invokeinterface #25,  1           // InterfaceMethod java/util/List.stream:()Ljava/util/stream/Stream;
     202: aload_2
     203: invokedynamic #125,  0            // InvokeDynamic #5:test:(Ljava/lang/String;)Ljava/util/function/Predicate;
     208: invokeinterface #35,  2           // InterfaceMethod java/util/stream/Stream.filter:(Ljava/util/function/Predicate;)Ljava/util/stream/Stream;
     213: invokeinterface #41,  1           // InterfaceMethod java/util/stream/Stream.findFirst:()Ljava/util/Optional;
     218: invokevirtual #82                 // Method java/util/Optional.get:()Ljava/lang/Object;
     221: checkcast     #55                 // class com/turbulence6th/dijkstra/Graph$Node
     224: astore        5
     226: getstatic     #126                // Field java/lang/System.out:Ljava/io/PrintStream;
     229: new           #132                // class java/lang/StringBuilder
     232: dup
     233: ldc           #134                // String Min distance:
     235: invokespecial #136                // Method java/lang/StringBuilder."<init>":(Ljava/lang/String;)V
     238: aload         5
     240: getfield      #85                 // Field com/turbulence6th/dijkstra/Graph$Node.minDistance:I
     243: invokevirtual #139                // Method java/lang/StringBuilder.append:(I)Ljava/lang/StringBuilder;
     246: invokevirtual #143                // Method java/lang/StringBuilder.toString:()Ljava/lang/String;
     249: invokevirtual #147                // Method java/io/PrintStream.println:(Ljava/lang/String;)V
     252: getstatic     #126                // Field java/lang/System.out:Ljava/io/PrintStream;
     255: aload         5
     257: getfield      #152                // Field com/turbulence6th/dijkstra/Graph$Node.data:Ljava/lang/String;
     260: invokevirtual #147                // Method java/io/PrintStream.println:(Ljava/lang/String;)V
     263: aload         5
     265: getfield      #115                // Field com/turbulence6th/dijkstra/Graph$Node.minEdge:Lcom/turbulence6th/dijkstra/Graph$Node;
     268: astore        5
     270: aload         5
     272: ifnonnull     252
     275: return

  public java.lang.String toString();
    Code:
       0: aload_0
       1: getfield      #17                 // Field nodes:Ljava/util/List;
       4: invokevirtual #171                // Method java/lang/Object.toString:()Ljava/lang/String;
       7: areturn

  static void access$0(com.turbulence6th.dijkstra.Graph, com.turbulence6th.dijkstra.Graph$Node);
    Code:
       0: aload_0
       1: aload_1
       2: invokespecial #174                // Method addNode:(Lcom/turbulence6th/dijkstra/Graph$Node;)V
       5: return
}
